altair_reveal/__init__.py
altair_reveal-0.0.3.dist-info/LICENSE
altair_reveal-0.0.3.dist-info/METADATA
altair_reveal-0.0.3.dist-info/WHEEL
altair_reveal-0.0.3.dist-info/top_level.txt
altair_reveal-0.0.3.dist-info/RECORD
